{
  "id": 59828,
  "updated_at": "30/03/2026 13:00:05",
  "price_eur": 58682.0,
  "change_24h_pct": 1.91,
  "high_24h_eur": 58968.0,
  "low_24h_eur": 56674.0,
  "support_eur": 58108.5,
  "resistance_eur": 59255.5,
  "bias": "moderatamente rialzista",
  "volatility": "media",
  "quick_read": "Prezzo in equilibrio nel breve. € 58.108 resta il supporto da difendere, mentre € 59.256 è la prima resistenza utile per un'accelerazione.",
  "latest_report_file": "Report_Finanziari/Report_Mondiale_30_03_2026_13_00.html"
}