{
  "id": 94137,
  "updated_at": "29/03/2026 12:30:01",
  "price_eur": 57551.0,
  "change_24h_pct": 0.46,
  "high_24h_eur": 58197.0,
  "low_24h_eur": 57268.0,
  "support_eur": 57318.75,
  "resistance_eur": 58197.0,
  "bias": "neutrale",
  "volatility": "contenuta",
  "quick_read": "Prezzo in equilibrio nel breve. € 57.319 resta il supporto da difendere, mentre € 58.197 è la prima resistenza utile per un'accelerazione.",
  "latest_report_file": "Report_Finanziari/Report_Mondiale_29_03_2026_12_30.html"
}