{
    "status": "OPERATIVO",
    "price": "€ 58.007,79",
    "signal": "BULLISH",
    "reliability": "97%",
    "last_update": "23:54:26",
    "ticker": "BTC/EUR: € 58.007,79 • KEYGAP SIGNAL: BULLISH • STATUS: ONLINE • UPDATE: 23:54:26 • ",
    "news": [
        {
            "time": "23:30",
            "text": "Binance Pushes Back on Senate Inquiry, Calls Allegations ‘False and Defamatory’ in Formal Response",
            "link": "https://news.bitcoin.com/binance-pushes-back-on-senate-inquiry-calls-allegations-false-and-defamatory-in-formal-response/"
        },
        {
            "time": "23:26",
            "text": "AI Agents Have Already Chosen Their Money: Bitcoin",
            "link": "https://www.forbes.com/sites/davidbirnbaum/2026/03/07/ai-agents-have-already-chosen-their-money-bitcoin/"
        },
        {
            "time": "23:20",
            "text": "Palantir's has the US Pentagon in a chokehold that threatens the entire world",
            "link": "https://www.cryptopolitan.com/palantir-pentagon-disgustingly-twisted-rship/"
        },
        {
            "time": "23:05",
            "text": "Crypto Fear and Greed Index falls back down to 'extreme fear' levels",
            "link": "https://cointelegraph.com/news/crypto-fear-greed-index-extreme-fear?utm_source=rss_feed&utm_medium=rss&utm_campaign=rss_partner_inbound"
        },
        {
            "time": "23:00",
            "text": "Analysts Predict Conservative XRP Price If It Follows 2017 Run",
            "link": "https://www.newsbtc.com/altcoin/analysts-predict-conservative-xrp-price-if-it-follows-2017-run/"
        },
        {
            "time": "22:30",
            "text": "The World’s Largest Asset Managers Hold MSTR: Strategy Highlights Massive Institutional Bitcoin Exposure",
            "link": "https://news.bitcoin.com/the-worlds-largest-asset-managers-hold-mstr-strategy-highlights-massive-institutional-bitcoin-exposure/"
        }
    ]
}