{
    "status": "OPERATIVO",
    "price": "€ 58.796,16",
    "signal": "BEARISH",
    "reliability": "97%",
    "last_update": "10:22:34",
    "ticker": "BTC/EUR: € 58.796,16 • KEYGAP SIGNAL: BEARISH • STATUS: ONLINE • UPDATE: 10:22:34 • ",
    "news": [
        {
            "time": "10:19",
            "text": "Bitcoin Options Traders Eye Rebound As Volatility Hits Three-Year High",
            "link": "https://seekingalpha.com/article/4879981-bitcoin-options-traders-eye-rebound-volatility-hits-three-year-high?utm_source=cryptocompare.com&utm_medium=referral&feed_item_type=article"
        },
        {
            "time": "10:15",
            "text": "GBP/USD Price Forecast: Critical Breakdown Below 1.3250 Signals Alarming Downward Momentum",
            "link": "https://bitcoinworld.co.in/gbp-usd-price-forecast-breakdown/"
        },
        {
            "time": "10:14",
            "text": "XRP's Key Indicators Converge, Building a Base For a Price Recovery",
            "link": "https://u.today/xrps-key-indicators-converge-will-it-spark-2-rally"
        },
        {
            "time": "10:12",
            "text": "Binance coin price prediction 2026-2032: How high will BNB go?",
            "link": "https://www.cryptopolitan.com/binance-coin-price-prediction/"
        },
        {
            "time": "10:10",
            "text": "Federal Reserve Faces Daunting Double Inflation Data Test, Deutsche Bank Warns",
            "link": "https://bitcoinworld.co.in/federal-reserve-double-inflation-test/"
        },
        {
            "time": "10:05",
            "text": "EUR/USD Analysis: Currency Pair Holds Steady Near 1.1550 Amid Intense Risk-Off Pressure",
            "link": "https://bitcoinworld.co.in/eur-usd-holds-losses-risk-off/"
        }
    ]
}